kedro_static_viz/__init__.py
kedro_static_viz/cli.py
kedro_static_viz/core.py
kedro_static_viz/hooks.py
kedro_static_viz/public.tar.gz
kedro_static_viz/vendored.py
kedro_static_viz-0.4.4.dist-info/LICENSE
kedro_static_viz-0.4.4.dist-info/METADATA
kedro_static_viz-0.4.4.dist-info/WHEEL
kedro_static_viz-0.4.4.dist-info/entry_points.txt
kedro_static_viz-0.4.4.dist-info/top_level.txt
kedro_static_viz-0.4.4.dist-info/RECORD
