Metadata-Version: 2.1
Name: kedro-static-viz
Version: 0.4.4
Summary: Creates a static visualization of your pipeline
Home-page: https://github.com/WaylonWalker/kedro-static-viz.git
Author: Waylon Walker
Author-email: waylon@waylonwalker.com
License: MIT
Platform: UNKNOWN
Classifier: License :: OSI Approved :: MIT License
Classifier: Programming Language :: Python :: 3.6
Classifier: Programming Language :: Python :: 3.7
Classifier: Programming Language :: Python :: 3.8
Requires-Dist: IPython
Requires-Dist: click
Requires-Dist: flask
Requires-Dist: kedro
Requires-Dist: kedro-viz
Requires-Dist: semver
Requires-Dist: toposort
